raphson_mp/__init__.py
raphson_mp/__main__.py
raphson_mp/py.typed
raphson_mp/cli/__init__.py
raphson_mp/cli/cli.py
raphson_mp/cli/download.py
raphson_mp/client/__init__.py
raphson_mp/client/playlist.py
raphson_mp/client/share.py
raphson_mp/client/track.py
raphson_mp/client/util.py
raphson_mp/common/__init__.py
raphson_mp/common/const.py
raphson_mp/common/control.py
raphson_mp/common/eventbus.py
raphson_mp/common/httpclient.py
raphson_mp/common/image.py
raphson_mp/common/io_response.py
raphson_mp/common/lyrics.py
raphson_mp/common/metadata.py
raphson_mp/common/music.py
raphson_mp/common/playlist.py
raphson_mp/common/process.py
raphson_mp/common/subsonic_typing.py
raphson_mp/common/tag.py
raphson_mp/common/track.py
raphson_mp/common/typing.py
raphson_mp/common/util.py
raphson_mp/migrations/0001-music.sql
raphson_mp/migrations/0002-music.sql
raphson_mp/migrations/0003-music.sql
raphson_mp/migrations/0004-music.sql
raphson_mp/migrations/0005-music.sql
raphson_mp/migrations/0006-offline.sql
raphson_mp/migrations/0007-music.sql
raphson_mp/migrations/0008-music.sql
raphson_mp/migrations/0009-music.sql
raphson_mp/migrations/0010-music.sql
raphson_mp/migrations/0011-music.sql
raphson_mp/migrations/0012-music.sql
raphson_mp/migrations/0013-music.sql
raphson_mp/migrations/0014-music.sql
raphson_mp/migrations/0015-music.sql
raphson_mp/migrations/0016-music.sql
raphson_mp/migrations/0017-music.sql
raphson_mp/migrations/0018-offline.sql
raphson_mp/migrations/0019-music.sql
raphson_mp/migrations/0020-music.sql
raphson_mp/migrations/0021-cache.sql
raphson_mp/migrations/0022-cache.sql
raphson_mp/migrations/0023-music.sql
raphson_mp/migrations/0024-music.sql
raphson_mp/migrations/0025-music.sql
raphson_mp/migrations/0026-music.sql
raphson_mp/migrations/0027-music.sql
raphson_mp/migrations/0028-music.sql
raphson_mp/migrations/0029-music.sql
raphson_mp/migrations/0030-music.sql
raphson_mp/migrations/0031-music.sql
raphson_mp/migrations/0032-music.sql
raphson_mp-2.12.0.dist-info/METADATA
raphson_mp-2.12.0.dist-info/WHEEL
raphson_mp-2.12.0.dist-info/entry_points.txt
raphson_mp-2.12.0.dist-info/RECORD
