Metadata-Version: 2.4
Name: raphson_mp
Version: 2.12.0
Summary: Raphson music player
Project-URL: Homepage, https://codeberg.org/raphson/music-server
Project-URL: Issues, https://codeberg.org/raphson/music-server/issues
Author-email: Robin Slot <robin@rslot.nl>
Classifier: Development Status :: 5 - Production/Stable
Classifier: Environment :: Console
Classifier: Framework :: Flask
Classifier: Intended Audience :: End Users/Desktop
Classifier: Natural Language :: Dutch
Classifier: Natural Language :: English
Classifier: Operating System :: POSIX
Classifier: Programming Language :: Python :: 3
Classifier: Topic :: Multimedia :: Sound/Audio :: Players
Classifier: Typing :: Typed
Requires-Python: >=3.11
Requires-Dist: aiohttp~=3.9
Requires-Dist: jinja2~=3.0
Requires-Dist: typing-extensions
Provides-Extra: dev
Requires-Dist: babel; extra == 'dev'
Requires-Dist: black; extra == 'dev'
Requires-Dist: build; extra == 'dev'
Requires-Dist: coverage; extra == 'dev'
Requires-Dist: isort; extra == 'dev'
Requires-Dist: pytest; extra == 'dev'
Requires-Dist: pytest-asyncio<2.0,>=0.26; extra == 'dev'
Requires-Dist: pytest-cov; extra == 'dev'
Requires-Dist: twine; extra == 'dev'
Requires-Dist: yappi; extra == 'dev'
Provides-Extra: extra
Requires-Dist: cryptography>=35.0; extra == 'extra'
Requires-Dist: prometheus-client>=0.15.0; extra == 'extra'
